django_app1/__init__.py
django_app1/admin.py
django_app1/apps.py
django_app1/models.py
django_app1/tests.py
django_app1/urls.py
django_app1/views.py
django_app1/migrations/__init__.py
django_app1-0.6.dist-info/licenses/LICENCE
django_app1-0.6.dist-info/METADATA
django_app1-0.6.dist-info/WHEEL
django_app1-0.6.dist-info/entry_points.txt
django_app1-0.6.dist-info/top_level.txt
django_app1-0.6.dist-info/RECORD
